1. 进入.class文件目录 执行 javap -v
字节码反编译

Classfile /D:/Workspaces/IDEASpace/deeps/jvm/target/classes/com/zhaojm/jvm/a_base/AaStackStudyTest.class
  Last modified 2020-5-9; size 501 bytes
  MD5 checksum e00f34ae9fe75f60f9e693d9356d1f8b
  Compiled from "AaStackStudyTest.java"
public class com.zhaojm.jvm.a_base.AaStackStudyTest
  minor version: 0
  major version: 52
  flags: ACC_PUBLIC, ACC_SUPER
Constant pool:
   #1 = Methodref          #3.#21         // java/lang/Object."<init>":()V
   #2 = Class              #22            // com/zhaojm/jvm/a_base/AaStackStudyTest
   #3 = Class              #23            // java/lang/Object
   #4 = Utf8               <init>
   #5 = Utf8               ()V
   #6 = Utf8               Code
   #7 = Utf8               LineNumberTable
   #8 = Utf8               LocalVariableTable
   #9 = Utf8               this
  #10 = Utf8               Lcom/zhaojm/jvm/a_base/AaStackStudyTest;
  #11 = Utf8               main
  #12 = Utf8               ([Ljava/lang/String;)V
  #13 = Utf8               args
  #14 = Utf8               [Ljava/lang/String;
  #15 = Utf8               i
  #16 = Utf8               I
  #17 = Utf8               j
  #18 = Utf8               k
  #19 = Utf8               SourceFile
  #20 = Utf8               AaStackStudyTest.java
  #21 = NameAndType        #4:#5          // "<init>":()V
  #22 = Utf8               com/zhaojm/jvm/a_base/AaStackStudyTest
  #23 = Utf8               java/lang/Object
{
  public com.zhaojm.jvm.a_base.AaStackStudyTest();
    descriptor: ()V
    flags: ACC_PUBLIC
    Code:
      stack=1, locals=1, args_size=1
         0: aload_0
         1: invokespecial #1                  // Method java/lang/Object."<init>":()V
         4: return
      LineNumberTable:
        line 7: 0
      LocalVariableTable:
        Start  Length  Slot  Name   Signature
            0       5     0  this   Lcom/zhaojm/jvm/a_base/AaStackStudyTest;

  public static void main(java.lang.String[]);
    descriptor: ([Ljava/lang/String;)V
    flags: ACC_PUBLIC, ACC_STATIC
    Code:
      stack=2, locals=4, args_size=1
         0: iconst_2
         1: istore_1
         2: iconst_3
         3: istore_2
         4: iload_1
         5: iload_2
         6: iadd
         7: istore_3
         8: return
      LineNumberTable:
        line 10: 0
        line 11: 2
        line 12: 4
        line 13: 8
      LocalVariableTable:
        Start  Length  Slot  Name   Signature
            0       9     0  args   [Ljava/lang/String;
            2       7     1     i   I
            4       5     2     j   I
            8       1     3     k   I
}
SourceFile: "AaStackStudyTest.java"


由于跨平台性的设计，Java的指令都是根据栈来设计的。

栈的指令集架构的特点
跨平台性，指令集小，指令多；执行性能比寄存器差。

jps  查看正在执行的进程